image_generator/__init__.py
image_generator/constants.py
image_generator/enums.py
image_generator/exceptions.py
image_generator/utils.py
image_generator/drake/__init__.py
image_generator/drake/core.py
image_generator/drake/drake_ayano_base.png
image_generator/drake/drake_chika_base.png
image_generator/drake/drake_sayori_base.webp
image_generator/drake/drake_sayori_confused_base.webp
image_generator/drake/drake_standard_base.png
image_generator/drake/registry.py
image_generator/jail/__init__.py
image_generator/jail/core.py
image_generator/jail/jail_base.png
image_generator/killed/__init__.py
image_generator/killed/core.py
image_generator/killed/killed_base.png
image_generator/pooh/__init__.py
image_generator/pooh/core.py
image_generator/pooh/pooh_base.png
image_generator/realization/__init__.py
image_generator/realization/core.py
image_generator/realization/realization_base.png
image_generator/ship/__init__.py
image_generator/ship/core.py
image_generator/ship/ship_base.png
image_generator/test_font/__init__.py
image_generator/test_font/core.py
image_generator/text_image/__init__.py
image_generator/text_image/core.py
image_generator/trash/__init__.py
image_generator/trash/core.py
image_generator/trash/hand_overlay.png
image_generator/trash/trash_base.png
image_generator/uno/__init__.py
image_generator/uno/core.py
image_generator/uno/uno_base.jpg
image_generator/uno/uno_no_number_base.png
image_generator/wolverine/__init__.py
image_generator/wolverine/core.py
image_generator/wolverine/wolverine_base.png
py_image_generator-1.7.1.dist-info/LICENSE
py_image_generator-1.7.1.dist-info/METADATA
py_image_generator-1.7.1.dist-info/WHEEL
py_image_generator-1.7.1.dist-info/top_level.txt
py_image_generator-1.7.1.dist-info/RECORD
