Metadata-Version: 2.1
Name: py-image-generator
Version: 1.7.1
Summary: Image Generator
Home-page: https://github.com/TheElementalOfDestruction/image-generator
Author: Destiny Peterson (The Elemental of Destruction)
Author-email: arceusthe@gmail.com
License: GPL
Download-URL: https://github.com/TheElementalOfDestruction/image-generator/archives/master
Platform: UNKNOWN
License-File: LICENSE
